mlx_hub/__init__.py
mlx_hub/cli.py
mlx_hub/core.py
mlx_hub/utils.py
mlx_hub/data/login_help.txt
mlx_hub/data/suggested_models.txt
mlx_hub-1.0.0.dist-info/LICENSE.txt
mlx_hub-1.0.0.dist-info/METADATA
mlx_hub-1.0.0.dist-info/WHEEL
mlx_hub-1.0.0.dist-info/entry_points.txt
mlx_hub-1.0.0.dist-info/top_level.txt
mlx_hub-1.0.0.dist-info/RECORD
