Metadata-Version: 2.1
Name: mlx-hub
Version: 1.0.0
Summary: A command line tool for downloading and managing MLX models
Author-email: Gaurav Aggarwal <gauravaggarwal@mail.com>
License: MIT License
Project-URL: Homepage, https://github.com/g-aggarwal/mlx-hub
Classifier: Programming Language :: Python :: 3
Classifier: License :: OSI Approved :: MIT License
Classifier: Operating System :: MacOS :: MacOS X
Requires-Python: >=3.6
License-File: LICENSE.txt
Requires-Dist: huggingface-hub >=0.23.4
